{
  "BRA": "Brazil",
  "YE": "Yemen",
  "RUS": "Russian Federation (the)",
  "AIA": "Anguilla",
  "NGA": "Nigeria",
  "QA": "Qatar",
  "MR": "Mauritania",
  "CH": "Switzerland",
  "ATG": "Antigua and Barbuda",
  "AF": "Afghanistan",
  "AO": "Angola",
  "BMU": "Bermuda",
  "BT": "Bhutan",
  "VUT": "Vanuatu",
  "HK": "Hong Kong",
  "CZE": "Czechia",
  "SGP": "Singapore",
  "CU": "Cuba",
  "HU": "Hungary",
  "SRB": "Serbia",
  "BRB": "Barbados",
  "AZ": "Azerbaijan",
  "DNK": "Denmark",
  "SXM": "Sint Maarten (Dutch part)",
  "SS": "South Sudan",
  "TKM": "Turkmenistan",
  "TTO": "Trinidad and Tobago",
  "BY": "Belarus",
  "MA": "Morocco",
  "SWZ": "Eswatini",
  "ZAF": "South Africa",
  "MZ": "Mozambique",
  "NAM": "Namibia",
  "TR": "Türkiye",
  "PL": "Poland",
  "GRL": "Greenland",
  "US": "United States of America (the)",
  "SR": "Suriname",
  "LR": "Liberia",
  "RWA": "Rwanda",
  "OM": "Oman",
  "MH": "Marshall Islands (the)",
  "TG": "Togo",
  "NIU": "Niue",
  "CW": "Curaçao",
  "IDN": "Indonesia",
  "MCO": "Monaco",
  "AT": "Austria",
  "CO": "Colombia",
  "SV": "El Salvador",
  "QAT": "Qatar",
  "NLD": "Netherlands (the)",
  "RE": "Réunion",
  "LI": "Liechtenstein",
  "PR": "Puerto Rico",
  "MDA": "Moldova (the Republic of)",
  "GI": "Gibraltar",
  "CV": "Cabo Verde",
  "JPN": "Japan",
  "KG": "Kyrgyzstan",
  "LVA": "Latvia",
  "SK": "Slovakia",
  "LT": "Lithuania",
  "EST": "Estonia",
  "AL": "Albania",
  "SVN": "Slovenia",
  "PLW": "Palau",
  "GMB": "Gambia (the)",
  "BL": "Saint Barthélemy",
  "FK": "Falkland Islands (the) [Malvinas]",
  "TV": "Tuvalu",
  "CCK": "Cocos (Keeling) Islands (the)",
  "ATA": "Antarctica",
  "ATF": "French Southern Territories (the)",
  "SJ": "Svalbard and Jan Mayen",
  "NPL": "Nepal",
  "HRV": "Croatia",
  "CAN": "Canada",
  "HTI": "Haiti",
  "CPV": "Cabo Verde",
  "CX": "Christmas Island",
  "GGY": "Guernsey",
  "ITA": "Italy",
  "VG": "Virgin Islands (British)",
  "ALA": "Åland Islands",
  "BEL": "Belgium",
  "VI": "Virgin Islands (U.S.)",
  "TON": "Tonga",
  "TT": "Trinidad and Tobago",
  "AI": "Anguilla",
  "TGO": "Togo",
  "GE": "Georgia",
  "GB": "United Kingdom of Great Britain and Northern Ireland (the)",
  "TW": "Taiwan (Province of China)",
  "BV": "Bouvet Island",
  "NRU": "Nauru",
  "FLK": "Falkland Islands (the) [Malvinas]",
  "AU": "Australia",
  "KOR": "Korea (the Republic of)",
  "VEN": "Venezuela (Bolivarian Republic of)",
  "PER": "Peru",
  "POL": "Poland",
  "CD": "Congo (the Democratic Republic of the)",
  "IL": "Israel",
  "FJ": "Fiji",
  "PRY": "Paraguay",
  "HM": "Heard Island and McDonald Islands",
  "PCN": "Pitcairn",
  "MO": "Macao",
  "ERI": "Eritrea",
  "MDG": "Madagascar",
  "LU": "Luxembourg",
  "JOR": "Jordan",
  "TH": "Thailand",
  "MSR": "Montserrat",
  "TZ": "Tanzania, the United Republic of",
  "VIR": "Virgin Islands (U.S.)",
  "MC": "Monaco",
  "KGZ": "Kyrgyzstan",
  "ABW": "Aruba",
  "BVT": "Bouvet Island",
  "LIE": "Liechtenstein",
  "MTQ": "Martinique",
  "SHN": "Saint Helena, Ascension and Tristan da Cunha",
  "AD": "Andorra",
  "DEU": "Germany",
  "IQ": "Iraq",
  "NI": "Nicaragua",
  "KW": "Kuwait",
  "TCA": "Turks and Caicos Islands (the)",
  "MW": "Malawi",
  "GH": "Ghana",
  "TUV": "Tuvalu",
  "ASM": "American Samoa",
  "DM": "Dominica",
  "EE": "Estonia",
  "IS": "Iceland",
  "IRL": "Ireland",
  "BM": "Bermuda",
  "TUN": "Tunisia",
  "MEX": "Mexico",
  "EC": "Ecuador",
  "CYP": "Cyprus",
  "LKA": "Sri Lanka",
  "BDI": "Burundi",
  "KM": "Comoros (the)",
  "SB": "Solomon Islands",
  "AE": "United Arab Emirates (the)",
  "CM": "Cameroon",
  "SYC": "Seychelles",
  "MAF": "Saint Martin (French part)",
  "EH": "Western Sahara*",
  "FIN": "Finland",
  "CC": "Cocos (Keeling) Islands (the)",
  "AS": "American Samoa",
  "KH": "Cambodia",
  "BLM": "Saint Barthélemy",
  "SJM": "Svalbard and Jan Mayen",
  "MD": "Moldova (the Republic of)",
  "NA": "Namibia",
  "SA": "Saudi Arabia",
  "SPM": "Saint Pierre and Miquelon",
  "SOM": "Somalia",
  "HN": "Honduras",
  "MK": "North Macedonia",
  "SSD": "South Sudan",
  "TWN": "Taiwan (Province of China)",
  "GTM": "Guatemala",
  "DZA": "Algeria",
  "GUF": "French Guiana",
  "MWI": "Malawi",
  "PRI": "Puerto Rico",
  "SWE": "Sweden",
  "LTU": "Lithuania",
  "LC": "Saint Lucia",
  "MYS": "Malaysia",
  "NOR": "Norway",
  "JAM": "Jamaica",
  "PA": "Panama",
  "UGA": "Uganda",
  "VC": "Saint Vincent and the Grenadines",
  "ETH": "Ethiopia",
  "GNB": "Guinea-Bissau",
  "ZMB": "Zambia",
  "TM": "Turkmenistan",
  "SI": "Slovenia",
  "GQ": "Equatorial Guinea",
  "PH": "Philippines (the)",
  "CZ": "Czechia",
  "ECU": "Ecuador",
  "BO": "Bolivia (Plurinational State of)",
  "NFK": "Norfolk Island",
  "SY": "Syrian Arab Republic (the)",
  "YEM": "Yemen",
  "LAO": "Lao People's Democratic Republic (the)",
  "DJI": "Djibouti",
  "BRN": "Brunei Darussalam",
  "LUX": "Luxembourg",
  "CMR": "Cameroon",
  "NO": "Norway",
  "TLS": "Timor-Leste",
  "IM": "Isle of Man",
  "CUB": "Cuba",
  "SX": "Sint Maarten (Dutch part)",
  "GG": "Guernsey",
  "CYM": "Cayman Islands (the)",
  "GW": "Guinea-Bissau",
  "GUY": "Guyana",
  "GHA": "Ghana",
  "MDV": "Maldives",
  "FJI": "Fiji",
  "JEY": "Jersey",
  "MNP": "Northern Mariana Islands (the)",
  "SH": "Saint Helena, Ascension and Tristan da Cunha",
  "BGR": "Bulgaria",
  "AFG": "Afghanistan",
  "NC": "New Caledonia",
  "USA": "United States of America (the)",
  "BE": "Belgium",
  "JP": "Japan",
  "MHL": "Marshall Islands (the)",
  "LV": "Latvia",
  "GLP": "Guadeloupe",
  "AM": "Armenia",
  "STP": "Sao Tome and Principe",
  "PNG": "Papua New Guinea",
  "KHM": "Cambodia",
  "SVK": "Slovakia",
  "TCD": "Chad",
  "SD": "Sudan (the)",
  "GT": "Guatemala",
  "IMN": "Isle of Man",
  "SUR": "Suriname",
  "BGD": "Bangladesh",
  "CHN": "China",
  "NZL": "New Zealand",
  "PAK": "Pakistan",
  "FRO": "Faroe Islands (the)",
  "PY": "Paraguay",
  "PHL": "Philippines (the)",
  "COG": "Congo (the)",
  "GBR": "United Kingdom of Great Britain and Northern Ireland (the)",
  "MN": "Mongolia",
  "TK": "Tokelau",
  "SAU": "Saudi Arabia",
  "DZ": "Algeria",
  "FSM": "Micronesia (Federated States of)",
  "PSE": "Palestine, State of",
  "KZ": "Kazakhstan",
  "LY": "Libya",
  "AW": "Aruba",
  "CRI": "Costa Rica",
  "UY": "Uruguay",
  "IRN": "Iran (Islamic Republic of)",
  "COM": "Comoros (the)",
  "SEN": "Senegal",
  "WSM": "Samoa",
  "GL": "Greenland",
  "BWA": "Botswana",
  "SN": "Senegal",
  "UM": "United States Minor Outlying Islands (the)",
  "UKR": "Ukraine",
  "JO": "Jordan",
  "MT": "Malta",
  "BS": "Bahamas (the)",
  "BI": "Burundi",
  "BA": "Bosnia and Herzegovina",
  "NIC": "Nicaragua",
  "MQ": "Martinique",
  "MU": "Mauritius",
  "MS": "Montserrat",
  "BEN": "Benin",
  "BW": "Botswana",
  "YT": "Mayotte",
  "MUS": "Mauritius",
  "PN": "Pitcairn",
  "MP": "Northern Mariana Islands (the)",
  "ESH": "Western Sahara*",
  "DMA": "Dominica",
  "ML": "Mali",
  "GNQ": "Equatorial Guinea",
  "VCT": "Saint Vincent and the Grenadines",
  "THA": "Thailand",
  "GIN": "Guinea",
  "MMR": "Myanmar",
  "FRA": "France",
  "TUR": "Türkiye",
  "BH": "Bahrain",
  "LB": "Lebanon",
  "PRT": "Portugal",
  "VNM": "Viet Nam",
  "AR": "Argentina",
  "KEN": "Kenya",
  "ESP": "Spain",
  "PG": "Papua New Guinea",
  "GR": "Greece",
  "HND": "Honduras",
  "HT": "Haiti",
  "WS": "Samoa",
  "SG": "Singapore",
  "KNA": "Saint Kitts and Nevis",
  "MOZ": "Mozambique",
  "GP": "Guadeloupe",
  "BF": "Burkina Faso",
  "ME": "Montenegro",
  "MAC": "Macao",
  "CAF": "Central African Republic (the)",
  "AQ": "Antarctica",
  "PK": "Pakistan",
  "REU": "Réunion",
  "BTN": "Bhutan",
  "SGS": "South Georgia and the South Sandwich Islands",
  "FM": "Micronesia (Federated States of)",
  "BHR": "Bahrain",
  "WLF": "Wallis and Futuna",
  "MV": "Maldives",
  "GS": "South Georgia and the South Sandwich Islands",
  "BN": "Brunei Darussalam",
  "CK": "Cook Islands (the)",
  "COL": "Colombia",
  "COD": "Congo (the Democratic Republic of the)",
  "IO": "British Indian Ocean Territory (the)",
  "AUT": "Austria",
  "BES": "Bonaire, Sint Eustatius and Saba",
  "BHS": "Bahamas (the)",
  "GAB": "Gabon",
  "SE": "Sweden",
  "PAN": "Panama",
  "SC": "Seychelles",
  "MRT": "Mauritania",
  "MLI": "Mali",
  "MAR": "Morocco",
  "KIR": "Kiribati",
  "NER": "Niger (the)",
  "ZW": "Zimbabwe",
  "SL": "Sierra Leone",
  "AG": "Antigua and Barbuda",
  "PF": "French Polynesia",
  "CF": "Central African Republic (the)",
  "BD": "Bangladesh",
  "AX": "Åland Islands",
  "SZ": "Eswatini",
  "ARE": "United Arab Emirates (the)",
  "SLE": "Sierra Leone",
  "GIB": "Gibraltar",
  "HR": "Croatia",
  "RS": "Serbia",
  "NF": "Norfolk Island",
  "AND": "Andorra",
  "CHE": "Switzerland",
  "IE": "Ireland",
  "NR": "Nauru",
  "ZA": "South Africa",
  "AZE": "Azerbaijan",
  "CA": "Canada",
  "KR": "Korea (the Republic of)",
  "VA": "Holy See (the)",
  "NU": "Niue",
  "JE": "Jersey",
  "CXR": "Christmas Island",
  "TD": "Chad",
  "IR": "Iran (Islamic Republic of)",
  "MNG": "Mongolia",
  "NL": "Netherlands (the)",
  "IND": "India",
  "BLZ": "Belize",
  "SLV": "El Salvador",
  "NCL": "New Caledonia",
  "BB": "Barbados",
  "FI": "Finland",
  "ZWE": "Zimbabwe",
  "UA": "Ukraine",
  "PRK": "Korea (the Democratic People's Republic of)",
  "ID": "Indonesia",
  "ARG": "Argentina",
  "ST": "Sao Tome and Principe",
  "VU": "Vanuatu",
  "VAT": "Holy See (the)",
  "RU": "Russian Federation (the)",
  "MNE": "Montenegro",
  "SLB": "Solomon Islands",
  "NE": "Niger (the)",
  "TO": "Tonga",
  "UZ": "Uzbekistan",
  "GN": "Guinea",
  "PYF": "French Polynesia",
  "BIH": "Bosnia and Herzegovina",
  "JM": "Jamaica",
  "CHL": "Chile",
  "FR": "France",
  "TL": "Timor-Leste",
  "ET": "Ethiopia",
  "KI": "Kiribati",
  "CG": "Congo (the)",
  "TJK": "Tajikistan",
  "DE": "Germany",
  "RW": "Rwanda",
  "DO": "Dominican Republic (the)",
  "HUN": "Hungary",
  "VE": "Venezuela (Bolivarian Republic of)",
  "BOL": "Bolivia (Plurinational State of)",
  "PW": "Palau",
  "TC": "Turks and Caicos Islands (the)",
  "ZM": "Zambia",
  "NG": "Nigeria",
  "WF": "Wallis and Futuna",
  "GF": "French Guiana",
  "MYT": "Mayotte",
  "LBY": "Libya",
  "TKL": "Tokelau",
  "LCA": "Saint Lucia",
  "KN": "Saint Kitts and Nevis",
  "ES": "Spain",
  "IRQ": "Iraq",
  "GM": "Gambia (the)",
  "URY": "Uruguay",
  "KP": "Korea (the Democratic People's Republic of)",
  "GY": "Guyana",
  "MX": "Mexico",
  "IN": "India",
  "SM": "San Marino",
  "GRC": "Greece",
  "BG": "Bulgaria",
  "MF": "Saint Martin (French part)",
  "SDN": "Sudan (the)",
  "CL": "Chile",
  "VN": "Viet Nam",
  "DOM": "Dominican Republic (the)",
  "HKG": "Hong Kong",
  "TZA": "Tanzania, the United Republic of",
  "NP": "Nepal",
  "CR": "Costa Rica",
  "ER": "Eritrea",
  "LK": "Sri Lanka",
  "CI": "Côte d'Ivoire",
  "BLR": "Belarus",
  "PT": "Portugal",
  "SYR": "Syrian Arab Republic (the)",
  "TJ": "Tajikistan",
  "MY": "Malaysia",
  "PS": "Palestine, State of",
  "PE": "Peru",
  "AGO": "Angola",
  "AUS": "Australia",
  "LS": "Lesotho",
  "KAZ": "Kazakhstan",
  "CY": "Cyprus",
  "ARM": "Armenia",
  "TN": "Tunisia",
  "GEO": "Georgia",
  "KY": "Cayman Islands (the)",
  "ISR": "Israel",
  "DK": "Denmark",
  "UZB": "Uzbekistan",
  "BZ": "Belize",
  "FO": "Faroe Islands (the)",
  "CIV": "Côte d'Ivoire",
  "GRD": "Grenada",
  "LA": "Lao People's Democratic Republic (the)",
  "RO": "Romania",
  "MKD": "North Macedonia",
  "KWT": "Kuwait",
  "COK": "Cook Islands (the)",
  "DJ": "Djibouti",
  "MLT": "Malta",
  "VGB": "Virgin Islands (British)",
  "ALB": "Albania",
  "EG": "Egypt",
  "KE": "Kenya",
  "UG": "Uganda",
  "MM": "Myanmar",
  "BQ": "Bonaire, Sint Eustatius and Saba",
  "ISL": "Iceland",
  "OMN": "Oman",
  "PM": "Saint Pierre and Miquelon",
  "ROU": "Romania",
  "BFA": "Burkina Faso",
  "GD": "Grenada",
  "LSO": "Lesotho",
  "GU": "Guam",
  "EGY": "Egypt",
  "UMI": "United States Minor Outlying Islands (the)",
  "CN": "China",
  "SO": "Somalia",
  "CUW": "Curaçao",
  "BJ": "Benin",
  "BR": "Brazil",
  "LBN": "Lebanon",
  "LBR": "Liberia",
  "HMD": "Heard Island and McDonald Islands",
  "GA": "Gabon",
  "GUM": "Guam",
  "NZ": "New Zealand",
  "MG": "Madagascar",
  "SMR": "San Marino",
  "IT": "Italy",
  "TF": "French Southern Territories (the)",
  "IOT": "British Indian Ocean Territory (the)"
}